bapt/__init__.py
bapt/cli.py
bapt/plotting.py
bapt-1.2.0.dist-info/METADATA
bapt-1.2.0.dist-info/WHEEL
bapt-1.2.0.dist-info/entry_points.txt
bapt-1.2.0.dist-info/top_level.txt
bapt-1.2.0.dist-info/RECORD
